cocodrilo/__init__.py
cocodrilo/cli.py
cocodrilo/cocodrilo.py
cocodrilo-0.1.0.dist-info/LICENSE
cocodrilo-0.1.0.dist-info/METADATA
cocodrilo-0.1.0.dist-info/WHEEL
cocodrilo-0.1.0.dist-info/entry_points.txt
cocodrilo-0.1.0.dist-info/RECORD
