Metadata-Version: 2.1
Name: cocodrilo
Version: 0.1.0
Summary: A large semiaquatic reptile.
Home-page: https://github.com/altaf-ali/cocodrilo
License: MIT
Author: Bruce Wayne
Author-email: altaf@fastmail.com
Requires-Python: >=3.9,<4.0
Classifier: Development Status :: 2 - Pre-Alpha
Classifier: Intended Audience :: Developers
Classifier: License :: OSI Approved :: MIT License
Classifier: Natural Language :: English
Classifier: Programming Language :: Python :: 3
Classifier: Programming Language :: Python :: 3.9
Classifier: Programming Language :: Python :: 3.10
Classifier: Programming Language :: Python :: 3.11
Requires-Dist: pip (>=23.1.2,<24.0.0)
Requires-Dist: typer (>=0.7.0,<0.8.0)
